sas_ipc_queue.cpython-39-x86_64-linux-gnu.so
sas_ipc_queue-0.9.1.dist-info/LICENSE
sas_ipc_queue-0.9.1.dist-info/METADATA
sas_ipc_queue-0.9.1.dist-info/top_level.txt
sas_ipc_queue-0.9.1.dist-info/RECORD
sas_ipc_queue-0.9.1.dist-info/WHEEL
