Metadata-Version: 2.1
Name: sas-ipc-queue
Version: 0.9.1
Summary: Bounded Interprocess Shared Memory Queue
Home-page: UNKNOWN
Author: Lawrence Lewis
Author-email: larry.lewis@sas.com
License: Apache 2.0
Platform: manylinux2014_x86_64
Requires-Python: >=3.6
License-File: LICENSE
